pyfive/__init__.py
pyfive/btree.py
pyfive/core.py
pyfive/dataobjects.py
pyfive/datatype_msg.py
pyfive/h5d.py
pyfive/h5py.py
pyfive/h5t.py
pyfive/high_level.py
pyfive/indexing.py
pyfive/inspect.py
pyfive/misc_low_level.py
pyfive/p5dump.py
pyfive/p5t.py
pyfive/utilities.py
pyfive-1.0.1.dist-info/METADATA
pyfive-1.0.1.dist-info/WHEEL
pyfive-1.0.1.dist-info/entry_points.txt
pyfive-1.0.1.dist-info/top_level.txt
pyfive-1.0.1.dist-info/RECORD
