Metadata-Version: 2.4
Name: pyfive
Version: 1.0.1
Summary: A pure python HDF5 reader
Author-email: Pyfive Development Team <valeriu.predoi@ncas.ac.uk>, Valeriu Predoi <valeriu.predoi@ncas.ac.uk>, David Hassell <david.hassell@ncas.ac.uk>, Bryan Lawrence <bryan.lawrence@ncas.ac.uk>, Jonathan Helmus <jjhelmus@gmail.com>, Kai Muehlbauer <kai.muehlbauer@uni-bonn.de>
License: BSD License, Version 3-Clause
Project-URL: Code, https://github.com/jjhelmus/pyfive
Project-URL: Issues, https://github.com/jjhelmus/pyfive/issues
Classifier: Development Status :: 5 - Production/Stable
Classifier: Environment :: Console
Classifier: Intended Audience :: Developers
Classifier: Intended Audience :: Science/Research
Classifier: License :: OSI Approved :: BSD License
Classifier: Natural Language :: English
Classifier: Operating System :: POSIX :: Linux
Classifier: Programming Language :: Python :: 3
Classifier: Programming Language :: Python :: 3.10
Classifier: Programming Language :: Python :: 3.11
Classifier: Programming Language :: Python :: 3.12
Classifier: Programming Language :: Python :: 3.13
Classifier: Programming Language :: Python :: 3.14
Classifier: Topic :: Scientific/Engineering
Classifier: Topic :: Scientific/Engineering :: Atmospheric Science
Classifier: Topic :: Scientific/Engineering :: Physics
Requires-Python: >=3.10
Requires-Dist: numpy>=2
Provides-Extra: test
Requires-Dist: pytest>6.0.0; extra == "test"
Requires-Dist: pytest-cov>=2.10.1; extra == "test"
Requires-Dist: pytest-html!=2.1.0; extra == "test"
Requires-Dist: pytest-rerunfailures; extra == "test"
Requires-Dist: pytest-xdist; extra == "test"
Requires-Dist: dask; extra == "test"
Requires-Dist: flake8; extra == "test"
Requires-Dist: flask; extra == "test"
Requires-Dist: flask-cors; extra == "test"
Requires-Dist: h5netcdf; extra == "test"
Requires-Dist: h5py; extra == "test"
Requires-Dist: netCDF4; extra == "test"
Requires-Dist: moto; extra == "test"
Requires-Dist: python-lzf; extra == "test"
Requires-Dist: s3fs>=2025.9.0; extra == "test"
Provides-Extra: doc
Requires-Dist: autodocsumm; extra == "doc"
Requires-Dist: sphinx; extra == "doc"
Requires-Dist: sphinx_rtd_theme; extra == "doc"
